face_parsing/__init__.py
face_parsing/cmd/__init__.py
face_parsing/cmd/cli.py
face_parsing/cmd/server.py
face_parsing/interfaces.py
face_parsing/model.py
face_parsing/resnet.py
image_preprocessing/README.md
image_preprocessing/__init__.py
image_preprocessing/basic_crop.py
image_preprocessing/create_alpha_blend_image.py
image_preprocessing/delete_region_other_than_below.py
image_preprocessing/interfaces.py
image_preprocessing/parse_converter.py
image_preprocessing/resize_square.py
image_preprocessing/shape_predictor_68_face_landmarks.dat
image_preprocessing/simple_crop.py
image_preprocessing/size_split.py
rembg/__init__.py
rembg/bg.py
rembg/cmd/__init__.py
rembg/cmd/cli.py
rembg/cmd/server.py
rembg/u2net/__init__.py
rembg/u2net/data_loader.py
rembg/u2net/detect.py
rembg/u2net/u2net.py
dg_util-0.0.32.dist-info/entry_points.txt
dg_util-0.0.32.dist-info/LICENSE
dg_util-0.0.32.dist-info/WHEEL
dg_util-0.0.32.dist-info/METADATA
dg_util-0.0.32.dist-info/RECORD
